dataframe_statistical_analyzer.py
dataframe_statistical_analyzer-1.0.2.dist-info/LICENSE
dataframe_statistical_analyzer-1.0.2.dist-info/METADATA
dataframe_statistical_analyzer-1.0.2.dist-info/WHEEL
dataframe_statistical_analyzer-1.0.2.dist-info/RECORD
