Metadata-Version: 2.1
Name: dataframe-statistical-analyzer
Version: 1.0.2
Summary: The `DataFrame Statistical Analyzer` package provides a utility tool for statistical analyzing in a Pandas DataFrame.
Home-page: https://github.com/DurgeshRathod/dataframe-statistical-analyzer
Keywords: time-series,data analysis,machine learning,statistics
Author: Durgesh Rathod
Requires-Python: >=3.11,<4.0
Classifier: Programming Language :: Python :: 3
Classifier: Programming Language :: Python :: 3.11
Classifier: Programming Language :: Python :: 3.12
Requires-Dist: matplotlib (>=3.9.1,<4.0.0)
Requires-Dist: numpy (>=2.0.0,<3.0.0)
Requires-Dist: pandas (>=2.2.2,<3.0.0)
Requires-Dist: scikit-learn (>=1.5.1,<2.0.0)
Requires-Dist: scipy (>=1.14.0,<2.0.0)
Requires-Dist: statsmodels (>=0.14.2,<0.15.0)
Project-URL: Repository, https://github.com/DurgeshRathod/dataframe-statistical-analyzer
